easyspex/__init__.py
easyspex/preprocessing.py
easyspex-0.0.1.dist-info/METADATA
easyspex-0.0.1.dist-info/WHEEL
easyspex-0.0.1.dist-info/top_level.txt
easyspex-0.0.1.dist-info/zip-safe
easyspex-0.0.1.dist-info/RECORD
